{"schema_version":"hew.sandbox.trace.v0","trace_id":"trace:hello-world","fixture_id":"hello-world","profile":"sandbox.sandbox-vm-export.v0","hew_version":"0.5.0-pre","sandbox_version":"0.0.0-spec","result":"ok","replay":{"seed":1,"step_budget":1000,"virtual_clock":{"epoch_ms":0,"tick_ms":1,"current_ms":0},"inputs":[]},"events":[{"seq":0,"type":"trace.started","phase":"run","span":null,"message":"fixture start"},{"seq":1,"type":"io.stdout","phase":"run","span":{"source_id":"src:main","path":"main.hew","start":{"byte_offset":16,"column":5,"line":2},"end":{"byte_offset":42,"column":31,"line":2}},"text":"Hello, sandbox!\n"},{"seq":2,"type":"trace.ended","phase":"run","span":null,"message":"ok"}],"final_state":{"status":"ok","exit_code":0,"step_count":5,"budget_remaining":995,"virtual_clock":{"epoch_ms":0,"tick_ms":1,"current_ms":0},"stdout":["Hello, sandbox!\n"],"stderr":[],"ids":{"actors":["actor:root"],"channels":[],"tasks":[],"supervisors":[],"machines":[]},"diagnostics":[],"sandbox_rejections":[],"runtime_failures":[],"globals":[]}}
