{"schema_version":"hew.sandbox.trace.v0","trace_id":"trace:enum-match","fixture_id":"enum-match","profile":"sandbox.educational.v0","hew_version":"0.5.0-pre","sandbox_version":"0.0.0-spec","result":"ok","replay":{"seed":5,"step_budget":1000,"virtual_clock":{"epoch_ms":0,"tick_ms":1,"current_ms":0},"inputs":[]},"events":[{"seq":0,"type":"trace.started","phase":"run","span":null,"message":"fixture start"},{"seq":1,"type":"io.stdout","phase":"run","span":null,"text":"24\n"},{"seq":2,"type":"trace.ended","phase":"run","span":null,"message":"ok"}],"final_state":{"status":"ok","exit_code":0,"step_count":10,"budget_remaining":990,"virtual_clock":{"epoch_ms":0,"tick_ms":1,"current_ms":0},"stdout":["24\n"],"stderr":[],"ids":{"actors":["actor:root"],"channels":[],"tasks":[],"supervisors":[],"machines":[]},"diagnostics":[],"sandbox_rejections":[],"runtime_failures":[],"globals":[]}}
